simba_sdk/__init__.py
simba_sdk/__init__.py~
simba_sdk/config.py
simba_sdk/core/__init__.py
simba_sdk/core/requests/__init__.py
simba_sdk/core/requests/auth/__init__.py
simba_sdk/core/requests/auth/token_store.py
simba_sdk/core/requests/client/__init__.py
simba_sdk/core/requests/client/base.py
simba_sdk/core/requests/client/credential/.client.py.swp
simba_sdk/core/requests/client/credential/.schemas.py.swp
simba_sdk/core/requests/client/credential/__init__.py
simba_sdk/core/requests/client/credential/client.py
simba_sdk/core/requests/client/credential/client.py~
simba_sdk/core/requests/client/credential/queries.py
simba_sdk/core/requests/client/credential/queries.py~
simba_sdk/core/requests/client/credential/schemas.py
simba_sdk/core/requests/client/members/__init__.py
simba_sdk/core/requests/client/members/client.py
simba_sdk/core/requests/client/members/queries.py
simba_sdk/core/requests/client/members/schemas.py
simba_sdk/core/requests/client/operator/__init__.py
simba_sdk/core/requests/client/operator/client.py
simba_sdk/core/requests/client/operator/queries.py
simba_sdk/core/requests/client/operator/schemas.py
simba_sdk/core/requests/client/resource/__init__.py
simba_sdk/core/requests/client/resource/client.py
simba_sdk/core/requests/client/resource/queries.py
simba_sdk/core/requests/client/resource/schemas.py
simba_sdk/core/requests/exception.py
simba_sdk/core/requests/middleware/__init__.py
simba_sdk/core/requests/middleware/manager.py
simba_sdk/core/requests/middleware/trailing_slash.py
simba_sdk/core/signing/__init__.py
simba_sdk/core/signing/ethereum.py
simba_sdk/core/signing/sign.py
simba_sdk/docs/assets/logo.svg
simba_sdk/docs/ensure/ensure.md
simba_sdk/docs/ensure/getting-started.md
simba_sdk/docs/ensure/signing.md
simba_sdk/docs/index.md
simba_sdk/docs/sessions/sessions.md
simba_sdk/docs/setup.md
simba_sdk/ensure/__init__.py
simba_sdk/ensure/client.py
simba_sdk/ensure/client.py~
simba_sdk/sessions/__init__.py
simba_sdk/sessions/base.py
simba_sdk-1.3.4.dist-info/LICENSE
simba_sdk-1.3.4.dist-info/METADATA
simba_sdk-1.3.4.dist-info/WHEEL
simba_sdk-1.3.4.dist-info/RECORD
